<?xml version="1.0" encoding="utf-8"?>

<bulleInfo>
	<play lang = "FRA">Lecture</play>
	<pause lang = "FRA">Pause</pause>
	<muteOn lang = "FRA">Son on</muteOn>
	<muteOff lang = "FRA">Son off</muteOff>
	<fullscreenOn lang = "FRA">Plein écran</fullscreenOn>
	<fullscreenOff lang = "FRA">Sortir du plein écran</fullscreenOff>
	<stOn lang = "FRA">Sous-titres On</stOn>
	<stOff lang = "FRA">Sous-titres Off</stOff>
	<pdf lang = "FRA">Transcript</pdf>
	<aide lang = "FRA">Aide</aide>
	
	<play lang = "ANG">Play</play>
	<pause lang = "ANG">Pause</pause>
	<muteOn lang = "ANG">Unmute</muteOn>
	<muteOff lang = "ANG">Mute</muteOff>
	<fullscreenOn lang = "ANG">Full screen</fullscreenOn>
	<fullscreenOff lang = "ANG">Exit full screen</fullscreenOff>
	<stOn lang = "ANG">Subtitles On</stOn>
	<stOff lang = "ANG">Subtitles Off</stOff>
	<pdf lang = "ANG">Transcript</pdf>
	<aide lang = "ANG">Help</aide>
	
</bulleInfo>